sciter/__init__.py
sciter/dom.py
sciter/error.py
sciter/event.py
sciter/host.py
sciter/platform.py
sciter/value.py
sciter/window.py
sciter/capi/__init__.py
sciter/capi/scapi.py
sciter/capi/scbehavior.py
sciter/capi/scdef.py
sciter/capi/scdom.py
sciter/capi/scgraphics.py
sciter/capi/scmsg.py
sciter/capi/screquest.py
sciter/capi/sctiscript.py
sciter/capi/sctypes.py
sciter/capi/scvalue.py
PySciter-0.6.9.dist-info/LICENSE
PySciter-0.6.9.dist-info/METADATA
PySciter-0.6.9.dist-info/WHEEL
PySciter-0.6.9.dist-info/top_level.txt
PySciter-0.6.9.dist-info/RECORD
