Metadata-Version: 2.1
Name: PySciter
Version: 0.6.9
Summary: Python bindings for the Sciter - Embeddable HTML/CSS/script engine (cross-platform desktop GUI toolkit).
Home-page: https://github.com/sciter-sdk/pysciter/
Download-URL: https://github.com/sciter-sdk/pysciter/releases
Author: pravic
Author-email: ehysta@gmail.com
License: MIT
Keywords: gui,sciter,javascript,tiscript,htmlayout,html,css,web,cross-platform
Platform: Windows
Platform: Linux
Platform: MacOS X
Classifier: Development Status :: 5 - Production/Stable
Classifier: Intended Audience :: Developers
Classifier: Operating System :: OS Independent
Classifier: Operating System :: Microsoft :: Windows :: Windows XP
Classifier: Operating System :: Microsoft :: Windows :: Windows Vista
Classifier: Operating System :: Microsoft :: Windows :: Windows 7
Classifier: Operating System :: Microsoft :: Windows :: Windows 10
Classifier: Operating System :: MacOS :: MacOS X
Classifier: Operating System :: POSIX :: Linux
Classifier: Environment :: MacOS X
Classifier: Environment :: Win32 (MS Windows)
Classifier: Environment :: X11 Applications :: GTK
Classifier: Environment :: Web Environment
Classifier: Programming Language :: C++
Classifier: Programming Language :: JavaScript
Classifier: Programming Language :: Python
Classifier: Programming Language :: Python :: 3
Classifier: Topic :: Desktop Environment
Classifier: Topic :: Software Development
Classifier: Topic :: Software Development :: Libraries :: Application Frameworks
Classifier: Topic :: Software Development :: Libraries :: Python Modules
Classifier: Topic :: Software Development :: User Interfaces
Classifier: Topic :: Software Development :: Widget Sets
License-File: LICENSE
